docs/__init__.py
docs/generator.py
have_a_rest/__init__.py
have_a_rest/fields.py
have_a_rest/json_response.py
have_a_rest/view.py
have_a_rest/ext/__init__.py
have_a_rest/ext/django/__init__.py
have_a_rest/ext/django/json_response.py
have_a_rest/ext/django/view.py
have_a_rest-0.1.3.dist-info/DESCRIPTION.rst
have_a_rest-0.1.3.dist-info/METADATA
have_a_rest-0.1.3.dist-info/RECORD
have_a_rest-0.1.3.dist-info/WHEEL
have_a_rest-0.1.3.dist-info/entry_points.txt
have_a_rest-0.1.3.dist-info/metadata.json
have_a_rest-0.1.3.dist-info/top_level.txt
