Metadata-Version: 2.0
Name: have-a-rest
Version: 0.1.3
Summary: Way to RESTfully describe your API
Home-page: https://github.com/torpedoallen/have-a-rest
Author: torpedoallen
Author-email: torpedoallen@gmail.com
License: MIT
Keywords: REST API Python
Platform: UNKNOWN
Requires-Dist: pytz
